embar/__init__.py
embar/config.py
embar/constraint.py
embar/constraint_base.py
embar/custom_types.py
embar/migration.py
embar/model.py
embar/py.typed
embar/sql.py
embar/sql_db.py
embar/table.py
embar/table_base.py
embar/column/__init__.py
embar/column/base.py
embar/column/common.py
embar/column/pg.py
embar/column/sqlite.py
embar/db/__init__.py
embar/db/_util.py
embar/db/base.py
embar/db/pg.py
embar/db/sqlite.py
embar/query/__init__.py
embar/query/clause_base.py
embar/query/conflict.py
embar/query/delete.py
embar/query/fns.py
embar/query/group_by.py
embar/query/having.py
embar/query/insert.py
embar/query/join.py
embar/query/many.py
embar/query/order_by.py
embar/query/query.py
embar/query/select.py
embar/query/update.py
embar/query/vector.py
embar/query/where.py
embar/tools/__init__.py
embar/tools/commands.py
embar/tools/fmt.py
embar/tools/llm.py
embar/tools/migrate.py
embar/tools/models.py
embar/tools/utils.py
embar-0.3.9.dist-info/METADATA
embar-0.3.9.dist-info/WHEEL
embar-0.3.9.dist-info/entry_points.txt
embar-0.3.9.dist-info/RECORD
