Metadata-Version: 2.4
Name: embar
Version: 0.3.9
Summary: A SQL-y and well-typed ORM for Python
Project-URL: homepage, https://github.com/carderne/embar
Project-URL: repository, https://github.com/carderne/embar
Author-email: Chris Arderne <chris@rdrn.me>
Keywords: ORM,SQL
Classifier: Intended Audience :: Developers
Classifier: Operating System :: OS Independent
Classifier: Programming Language :: Python
Classifier: Programming Language :: Python :: 3
Classifier: Programming Language :: Python :: 3.14
Classifier: Topic :: Database :: Front-Ends
Requires-Python: >=3.14
Requires-Dist: psycopg-pool>=3.3.0
Requires-Dist: psycopg[binary]>=3.2.11
Requires-Dist: pydantic>=2.12.4
